smartify
