Metadata-Version: 1.0
Name: smartify
Version: 0.0.1.alpha8
Summary: Make your python development easier
Home-page: https://github.com/lqj679ssn/smartify
Author: Adel Liu
Author-email: i@6-79.cn
License: MIT Licence
Keywords: easy,smart,field detect,error handle
Platform: any
